{
  "name": "Symbol173",
  "layers": [
    {
      "frames": [
        {
          "parts": [
            {
              "name": "REPLACE|Symbol156|REPLACE",
              "layers": [],
              "type": "symbol",
              "partIdx": 1,
              "transform": {
                "tx": -0.35,
                "ty": -7.4
              }
            }
          ]
        },
        {
          "parts": [
            {
              "name": "REPLACE|Symbol163|REPLACE",
              "layers": [],
              "type": "symbol",
              "partIdx": 1,
              "transform": {
                "tx": -4.9,
                "ty": 0.6,
                "a": 0.804779052734375,
                "d": 0.9352569580078125,
                "b": 0,
                "c": 0.2011871337890625
              }
            }
          ]
        },
        {
          "parts": [
            {
              "name": "REPLACE|Symbol165|REPLACE",
              "layers": [],
              "type": "symbol",
              "partIdx": 2,
              "transform": {
                "tx": -5.85,
                "ty": -10.65
              }
            }
          ]
        },
        {
          "parts": [
            {
              "name": "REPLACE|Symbol172|REPLACE",
              "layers": [],
              "type": "symbol",
              "partIdx": 1,
              "transform": {
                "tx": -13.35,
                "ty": -30.75
              }
            }
          ]
        },
        {
          "parts": [
            {
              "name": "REPLACE|Symbol149|REPLACE",
              "layers": [],
              "type": "symbol",
              "partIdx": 2,
              "colorOffset": {
                "r": -110,
                "g": -90,
                "b": -80
              },
              "transform": {
                "tx": 0.05,
                "ty": -12.65,
                "a": 1.068756103515625,
                "d": 1.0053558349609375
              }
            }
          ]
        }
      ]
    }
  ],
  "type": "symbol"
}