{
  "type": "symbol",
  "name": "Symbol504",
  "parts": [
    {
      "type": "symbol",
      "name": "Symbol452"
    },
    {
      "type": "symbol",
      "name": "Symbol426"
    },
    {
      "type": "symbol",
      "name": "Symbol411"
    },
    {
      "type": "symbol",
      "name": "Symbol342"
    },
    {
      "type": "symbol",
      "name": "Symbol105"
    },
    {
      "type": "symbol",
      "name": "Symbol80"
    }
  ],
  "frames": [
    [
      {
        "type": "symbol",
        "name": "Symbol80",
        "transform": {
          "tx": 10.15,
          "ty": -6.05,
          "a": -0.5104217529296875,
          "d": 0.5104217529296875,
          "b": 0.254852294921875,
          "c": 0.254852294921875
        }
      },
      {
        "type": "symbol",
        "name": "Symbol105",
        "transform": {
          "tx": 8.75,
          "ty": -12.45,
          "a": -0.5104217529296875,
          "d": 0.5104217529296875,
          "b": 0.254852294921875,
          "c": 0.254852294921875
        }
      },
      {
        "type": "symbol",
        "name": "Symbol342",
        "transform": {
          "tx": 5.95,
          "ty": -4.9,
          "a": -0.5714263916015625,
          "d": 0.5714263916015625
        }
      },
      {
        "type": "symbol",
        "name": "Symbol411",
        "transform": {
          "tx": 2.8,
          "ty": -32.7,
          "a": -0.5714263916015625,
          "d": 0.5714263916015625
        }
      },
      {
        "type": "symbol",
        "name": "Symbol426",
        "transform": {
          "tx": -6.5,
          "ty": -1.85,
          "a": -0.5714263916015625,
          "d": 0.5714263916015625
        }
      },
      {
        "type": "symbol",
        "name": "Symbol452",
        "transform": {
          "tx": -4.85,
          "ty": -8.2,
          "a": -0.5714263916015625,
          "d": 0.5714263916015625
        }
      }
    ],
    [
      {
        "type": "symbol",
        "name": "Symbol80",
        "transform": {
          "tx": 10.15,
          "ty": -6.05,
          "a": -0.5104217529296875,
          "d": 0.5104217529296875,
          "b": 0.254852294921875,
          "c": 0.254852294921875
        }
      },
      {
        "type": "symbol",
        "name": "Symbol105",
        "transform": {
          "tx": 8.75,
          "ty": -12.45,
          "a": -0.5104217529296875,
          "d": 0.5104217529296875,
          "b": 0.254852294921875,
          "c": 0.254852294921875
        }
      },
      {
        "type": "symbol",
        "name": "Symbol342",
        "transform": {
          "tx": 5.95,
          "ty": -4.9,
          "a": -0.5714263916015625,
          "d": 0.5714263916015625
        }
      },
      {
        "type": "symbol",
        "name": "Symbol411",
        "transform": {
          "tx": 2.8,
          "ty": -32.7,
          "a": -0.5714263916015625,
          "d": 0.5714263916015625
        }
      },
      {
        "type": "symbol",
        "name": "Symbol426",
        "transform": {
          "tx": -6.5,
          "ty": -1.85,
          "a": -0.5714263916015625,
          "d": 0.5714263916015625
        }
      },
      {
        "type": "symbol",
        "name": "Symbol452",
        "transform": {
          "tx": -4.85,
          "ty": -8.2,
          "a": -0.5714263916015625,
          "d": 0.5714263916015625
        }
      }
    ],
    [
      {
        "type": "symbol",
        "name": "Symbol80",
        "transform": {
          "tx": 10.15,
          "ty": -6.05,
          "a": -0.5104217529296875,
          "d": 0.5104217529296875,
          "b": 0.254852294921875,
          "c": 0.254852294921875
        }
      },
      {
        "type": "symbol",
        "name": "Symbol105",
        "transform": {
          "tx": 8.75,
          "ty": -12.45,
          "a": -0.5104217529296875,
          "d": 0.5104217529296875,
          "b": 0.254852294921875,
          "c": 0.254852294921875
        }
      },
      {
        "type": "symbol",
        "name": "Symbol342",
        "transform": {
          "tx": 5.95,
          "ty": -4.9,
          "a": -0.5714263916015625,
          "d": 0.5714263916015625
        }
      },
      {
        "type": "symbol",
        "name": "Symbol411",
        "transform": {
          "tx": 2.8,
          "ty": -32.7,
          "a": -0.5714263916015625,
          "d": 0.5714263916015625
        }
      },
      {
        "type": "symbol",
        "name": "Symbol426",
        "transform": {
          "tx": -6.5,
          "ty": -1.85,
          "a": -0.5714263916015625,
          "d": 0.5714263916015625
        }
      },
      {
        "type": "symbol",
        "name": "Symbol452",
        "transform": {
          "tx": -4.85,
          "ty": -8.2,
          "a": -0.5714263916015625,
          "d": 0.5714263916015625
        }
      }
    ],
    [
      {
        "type": "symbol",
        "name": "Symbol80",
        "transform": {
          "tx": 10.15,
          "ty": -6.05,
          "a": -0.5104217529296875,
          "d": 0.5104217529296875,
          "b": 0.254852294921875,
          "c": 0.254852294921875
        }
      },
      {
        "type": "symbol",
        "name": "Symbol105",
        "transform": {
          "tx": 8.75,
          "ty": -12.45,
          "a": -0.5104217529296875,
          "d": 0.5104217529296875,
          "b": 0.254852294921875,
          "c": 0.254852294921875
        }
      },
      {
        "type": "symbol",
        "name": "Symbol342",
        "transform": {
          "tx": 5.95,
          "ty": -4.9,
          "a": -0.5714263916015625,
          "d": 0.5714263916015625
        }
      },
      {
        "type": "symbol",
        "name": "Symbol411",
        "transform": {
          "tx": 2.8,
          "ty": -32.7,
          "a": -0.5714263916015625,
          "d": 0.5714263916015625
        }
      },
      {
        "type": "symbol",
        "name": "Symbol426",
        "transform": {
          "tx": -6.5,
          "ty": -1.85,
          "a": -0.5714263916015625,
          "d": 0.5714263916015625
        }
      },
      {
        "type": "symbol",
        "name": "Symbol452",
        "transform": {
          "tx": -4.85,
          "ty": -8.2,
          "a": -0.5714263916015625,
          "d": 0.5714263916015625
        }
      }
    ],
    [
      {
        "type": "symbol",
        "name": "Symbol80",
        "transform": {
          "tx": 10.15,
          "ty": -6.05,
          "a": -0.5104217529296875,
          "d": 0.5104217529296875,
          "b": 0.254852294921875,
          "c": 0.254852294921875
        }
      },
      {
        "type": "symbol",
        "name": "Symbol105",
        "transform": {
          "tx": 8.75,
          "ty": -12.45,
          "a": -0.5104217529296875,
          "d": 0.5104217529296875,
          "b": 0.254852294921875,
          "c": 0.254852294921875
        }
      },
      {
        "type": "symbol",
        "name": "Symbol342",
        "transform": {
          "tx": 5.95,
          "ty": -4.9,
          "a": -0.5714263916015625,
          "d": 0.5714263916015625
        }
      },
      {
        "type": "symbol",
        "name": "Symbol411",
        "transform": {
          "tx": 2.8,
          "ty": -32.7,
          "a": -0.5714263916015625,
          "d": 0.5714263916015625
        }
      },
      {
        "type": "symbol",
        "name": "Symbol426",
        "transform": {
          "tx": -6.5,
          "ty": -1.85,
          "a": -0.5714263916015625,
          "d": 0.5714263916015625
        }
      },
      {
        "type": "symbol",
        "name": "Symbol452",
        "transform": {
          "tx": -4.85,
          "ty": -8.2,
          "a": -0.5714263916015625,
          "d": 0.5714263916015625
        }
      }
    ],
    [
      {
        "type": "symbol",
        "name": "Symbol80",
        "transform": {
          "tx": 10.15,
          "ty": -6.05,
          "a": -0.5104217529296875,
          "d": 0.5104217529296875,
          "b": 0.254852294921875,
          "c": 0.254852294921875
        }
      },
      {
        "type": "symbol",
        "name": "Symbol105",
        "transform": {
          "tx": 8.75,
          "ty": -12.45,
          "a": -0.5104217529296875,
          "d": 0.5104217529296875,
          "b": 0.254852294921875,
          "c": 0.254852294921875
        }
      },
      {
        "type": "symbol",
        "name": "Symbol342",
        "transform": {
          "tx": 5.95,
          "ty": -4.9,
          "a": -0.5714263916015625,
          "d": 0.5714263916015625
        }
      },
      {
        "type": "symbol",
        "name": "Symbol411",
        "transform": {
          "tx": 2.8,
          "ty": -32.7,
          "a": -0.5714263916015625,
          "d": 0.5714263916015625
        }
      },
      {
        "type": "symbol",
        "name": "Symbol426",
        "transform": {
          "tx": -6.5,
          "ty": -1.85,
          "a": -0.5714263916015625,
          "d": 0.5714263916015625
        }
      },
      {
        "type": "symbol",
        "name": "Symbol452",
        "transform": {
          "tx": -4.85,
          "ty": -8.2,
          "a": -0.5714263916015625,
          "d": 0.5714263916015625
        }
      }
    ],
    [
      {
        "type": "symbol",
        "name": "Symbol80",
        "transform": {
          "tx": 10.15,
          "ty": -6.05,
          "a": -0.5104217529296875,
          "d": 0.5104217529296875,
          "b": 0.254852294921875,
          "c": 0.254852294921875
        }
      },
      {
        "type": "symbol",
        "name": "Symbol105",
        "transform": {
          "tx": 8.75,
          "ty": -12.45,
          "a": -0.5104217529296875,
          "d": 0.5104217529296875,
          "b": 0.254852294921875,
          "c": 0.254852294921875
        }
      },
      {
        "type": "symbol",
        "name": "Symbol342",
        "transform": {
          "tx": 5.95,
          "ty": -4.9,
          "a": -0.5714263916015625,
          "d": 0.5714263916015625
        }
      },
      {
        "type": "symbol",
        "name": "Symbol411",
        "transform": {
          "tx": 2.8,
          "ty": -32.7,
          "a": -0.5714263916015625,
          "d": 0.5714263916015625
        }
      },
      {
        "type": "symbol",
        "name": "Symbol426",
        "transform": {
          "tx": -6.5,
          "ty": -1.85,
          "a": -0.5714263916015625,
          "d": 0.5714263916015625
        }
      },
      {
        "type": "symbol",
        "name": "Symbol452",
        "transform": {
          "tx": -4.85,
          "ty": -8.2,
          "a": -0.5714263916015625,
          "d": 0.5714263916015625
        }
      }
    ],
    [
      {
        "type": "symbol",
        "name": "Symbol80",
        "transform": {
          "tx": 10.15,
          "ty": -6.05,
          "a": -0.5104217529296875,
          "d": 0.5104217529296875,
          "b": 0.254852294921875,
          "c": 0.254852294921875
        }
      },
      {
        "type": "symbol",
        "name": "Symbol105",
        "transform": {
          "tx": 8.75,
          "ty": -12.45,
          "a": -0.5104217529296875,
          "d": 0.5104217529296875,
          "b": 0.254852294921875,
          "c": 0.254852294921875
        }
      },
      {
        "type": "symbol",
        "name": "Symbol342",
        "transform": {
          "tx": 5.95,
          "ty": -4.9,
          "a": -0.5714263916015625,
          "d": 0.5714263916015625
        }
      },
      {
        "type": "symbol",
        "name": "Symbol411",
        "transform": {
          "tx": 2.8,
          "ty": -32.7,
          "a": -0.5714263916015625,
          "d": 0.5714263916015625
        }
      },
      {
        "type": "symbol",
        "name": "Symbol426",
        "transform": {
          "tx": -6.5,
          "ty": -1.85,
          "a": -0.5714263916015625,
          "d": 0.5714263916015625
        }
      },
      {
        "type": "symbol",
        "name": "Symbol452",
        "transform": {
          "tx": -4.85,
          "ty": -8.2,
          "a": -0.5714263916015625,
          "d": 0.5714263916015625
        }
      }
    ],
    [
      {
        "type": "symbol",
        "name": "Symbol80",
        "transform": {
          "tx": 10.15,
          "ty": -6.05,
          "a": -0.5104217529296875,
          "d": 0.5104217529296875,
          "b": 0.254852294921875,
          "c": 0.254852294921875
        }
      },
      {
        "type": "symbol",
        "name": "Symbol105",
        "transform": {
          "tx": 8.75,
          "ty": -12.45,
          "a": -0.5104217529296875,
          "d": 0.5104217529296875,
          "b": 0.254852294921875,
          "c": 0.254852294921875
        }
      },
      {
        "type": "symbol",
        "name": "Symbol342",
        "transform": {
          "tx": 5.95,
          "ty": -4.9,
          "a": -0.5714263916015625,
          "d": 0.5714263916015625
        }
      },
      {
        "type": "symbol",
        "name": "Symbol411",
        "transform": {
          "tx": 2.8,
          "ty": -32.7,
          "a": -0.5714263916015625,
          "d": 0.5714263916015625
        }
      },
      {
        "type": "symbol",
        "name": "Symbol426",
        "transform": {
          "tx": -6.5,
          "ty": -1.85,
          "a": -0.5714263916015625,
          "d": 0.5714263916015625
        }
      },
      {
        "type": "symbol",
        "name": "Symbol452",
        "transform": {
          "tx": -4.85,
          "ty": -8.2,
          "a": -0.5714263916015625,
          "d": 0.5714263916015625
        }
      }
    ],
    [
      {
        "type": "symbol",
        "name": "Symbol80",
        "transform": {
          "tx": 10.15,
          "ty": -6.05,
          "a": -0.5104217529296875,
          "d": 0.5104217529296875,
          "b": 0.254852294921875,
          "c": 0.254852294921875
        }
      },
      {
        "type": "symbol",
        "name": "Symbol105",
        "transform": {
          "tx": 8.75,
          "ty": -12.45,
          "a": -0.5104217529296875,
          "d": 0.5104217529296875,
          "b": 0.254852294921875,
          "c": 0.254852294921875
        }
      },
      {
        "type": "symbol",
        "name": "Symbol342",
        "transform": {
          "tx": 5.95,
          "ty": -4.9,
          "a": -0.5714263916015625,
          "d": 0.5714263916015625
        }
      },
      {
        "type": "symbol",
        "name": "Symbol411",
        "transform": {
          "tx": 2.8,
          "ty": -32.7,
          "a": -0.5714263916015625,
          "d": 0.5714263916015625
        }
      },
      {
        "type": "symbol",
        "name": "Symbol426",
        "transform": {
          "tx": -6.5,
          "ty": -1.85,
          "a": -0.5714263916015625,
          "d": 0.5714263916015625
        }
      },
      {
        "type": "symbol",
        "name": "Symbol452",
        "transform": {
          "tx": -4.85,
          "ty": -8.2,
          "a": -0.5714263916015625,
          "d": 0.5714263916015625
        }
      }
    ],
    [
      {
        "type": "symbol",
        "name": "Symbol80",
        "transform": {
          "tx": 10.15,
          "ty": -6.05,
          "a": -0.5104217529296875,
          "d": 0.5104217529296875,
          "b": 0.254852294921875,
          "c": 0.254852294921875
        }
      },
      {
        "type": "symbol",
        "name": "Symbol105",
        "transform": {
          "tx": 8.75,
          "ty": -12.45,
          "a": -0.5104217529296875,
          "d": 0.5104217529296875,
          "b": 0.254852294921875,
          "c": 0.254852294921875
        }
      },
      {
        "type": "symbol",
        "name": "Symbol342",
        "transform": {
          "tx": 5.95,
          "ty": -4.9,
          "a": -0.5714263916015625,
          "d": 0.5714263916015625
        }
      },
      {
        "type": "symbol",
        "name": "Symbol411",
        "transform": {
          "tx": 2.8,
          "ty": -32.7,
          "a": -0.5714263916015625,
          "d": 0.5714263916015625
        }
      },
      {
        "type": "symbol",
        "name": "Symbol426",
        "transform": {
          "tx": -6.5,
          "ty": -1.85,
          "a": -0.5714263916015625,
          "d": 0.5714263916015625
        }
      },
      {
        "type": "symbol",
        "name": "Symbol452",
        "transform": {
          "tx": -4.85,
          "ty": -8.2,
          "a": -0.5714263916015625,
          "d": 0.5714263916015625
        }
      }
    ],
    [
      {
        "type": "symbol",
        "name": "Symbol80",
        "transform": {
          "tx": 10.15,
          "ty": -6.05,
          "a": -0.5104217529296875,
          "d": 0.5104217529296875,
          "b": 0.254852294921875,
          "c": 0.254852294921875
        }
      },
      {
        "type": "symbol",
        "name": "Symbol105",
        "transform": {
          "tx": 8.75,
          "ty": -12.45,
          "a": -0.5104217529296875,
          "d": 0.5104217529296875,
          "b": 0.254852294921875,
          "c": 0.254852294921875
        }
      },
      {
        "type": "symbol",
        "name": "Symbol342",
        "transform": {
          "tx": 5.95,
          "ty": -4.9,
          "a": -0.5714263916015625,
          "d": 0.5714263916015625
        }
      },
      {
        "type": "symbol",
        "name": "Symbol411",
        "transform": {
          "tx": 2.8,
          "ty": -32.7,
          "a": -0.5714263916015625,
          "d": 0.5714263916015625
        }
      },
      {
        "type": "symbol",
        "name": "Symbol426",
        "transform": {
          "tx": -6.5,
          "ty": -1.85,
          "a": -0.5714263916015625,
          "d": 0.5714263916015625
        }
      },
      {
        "type": "symbol",
        "name": "Symbol452",
        "transform": {
          "tx": -4.85,
          "ty": -8.2,
          "a": -0.5714263916015625,
          "d": 0.5714263916015625
        }
      }
    ],
    [
      {
        "type": "symbol",
        "name": "Symbol80",
        "transform": {
          "tx": 10.15,
          "ty": -6.05,
          "a": -0.5104217529296875,
          "d": 0.5104217529296875,
          "b": 0.254852294921875,
          "c": 0.254852294921875
        }
      },
      {
        "type": "symbol",
        "name": "Symbol105",
        "transform": {
          "tx": 8.75,
          "ty": -12.45,
          "a": -0.5104217529296875,
          "d": 0.5104217529296875,
          "b": 0.254852294921875,
          "c": 0.254852294921875
        }
      },
      {
        "type": "symbol",
        "name": "Symbol342",
        "transform": {
          "tx": 5.95,
          "ty": -4.9,
          "a": -0.5714263916015625,
          "d": 0.5714263916015625
        }
      },
      {
        "type": "symbol",
        "name": "Symbol411",
        "transform": {
          "tx": 2.8,
          "ty": -32.7,
          "a": -0.5714263916015625,
          "d": 0.5714263916015625
        }
      },
      {
        "type": "symbol",
        "name": "Symbol426",
        "transform": {
          "tx": -6.5,
          "ty": -1.85,
          "a": -0.5714263916015625,
          "d": 0.5714263916015625
        }
      },
      {
        "type": "symbol",
        "name": "Symbol452",
        "transform": {
          "tx": -4.85,
          "ty": -8.2,
          "a": -0.5714263916015625,
          "d": 0.5714263916015625
        }
      }
    ],
    [
      {
        "type": "symbol",
        "name": "Symbol80",
        "transform": {
          "tx": 10.15,
          "ty": -6.05,
          "a": -0.5104217529296875,
          "d": 0.5104217529296875,
          "b": 0.254852294921875,
          "c": 0.254852294921875
        }
      },
      {
        "type": "symbol",
        "name": "Symbol105",
        "transform": {
          "tx": 8.75,
          "ty": -12.45,
          "a": -0.5104217529296875,
          "d": 0.5104217529296875,
          "b": 0.254852294921875,
          "c": 0.254852294921875
        }
      },
      {
        "type": "symbol",
        "name": "Symbol342",
        "transform": {
          "tx": 5.95,
          "ty": -4.9,
          "a": -0.5714263916015625,
          "d": 0.5714263916015625
        }
      },
      {
        "type": "symbol",
        "name": "Symbol411",
        "transform": {
          "tx": 2.8,
          "ty": -32.7,
          "a": -0.5714263916015625,
          "d": 0.5714263916015625
        }
      },
      {
        "type": "symbol",
        "name": "Symbol426",
        "transform": {
          "tx": -6.5,
          "ty": -1.85,
          "a": -0.5714263916015625,
          "d": 0.5714263916015625
        }
      },
      {
        "type": "symbol",
        "name": "Symbol452",
        "transform": {
          "tx": -4.85,
          "ty": -8.2,
          "a": -0.5714263916015625,
          "d": 0.5714263916015625
        }
      }
    ],
    [
      {
        "type": "symbol",
        "name": "Symbol80",
        "transform": {
          "tx": 10.15,
          "ty": -6.05,
          "a": -0.5104217529296875,
          "d": 0.5104217529296875,
          "b": 0.254852294921875,
          "c": 0.254852294921875
        }
      },
      {
        "type": "symbol",
        "name": "Symbol105",
        "transform": {
          "tx": 8.75,
          "ty": -12.45,
          "a": -0.5104217529296875,
          "d": 0.5104217529296875,
          "b": 0.254852294921875,
          "c": 0.254852294921875
        }
      },
      {
        "type": "symbol",
        "name": "Symbol342",
        "transform": {
          "tx": 5.95,
          "ty": -4.9,
          "a": -0.5714263916015625,
          "d": 0.5714263916015625
        }
      },
      {
        "type": "symbol",
        "name": "Symbol411",
        "transform": {
          "tx": 2.8,
          "ty": -32.7,
          "a": -0.5714263916015625,
          "d": 0.5714263916015625
        }
      },
      {
        "type": "symbol",
        "name": "Symbol426",
        "transform": {
          "tx": -6.5,
          "ty": -1.85,
          "a": -0.5714263916015625,
          "d": 0.5714263916015625
        }
      },
      {
        "type": "symbol",
        "name": "Symbol452",
        "transform": {
          "tx": -4.85,
          "ty": -8.2,
          "a": -0.5714263916015625,
          "d": 0.5714263916015625
        }
      }
    ],
    [
      {
        "type": "symbol",
        "name": "Symbol80",
        "transform": {
          "tx": 10.15,
          "ty": -6.05,
          "a": -0.5104217529296875,
          "d": 0.5104217529296875,
          "b": 0.254852294921875,
          "c": 0.254852294921875
        }
      },
      {
        "type": "symbol",
        "name": "Symbol105",
        "transform": {
          "tx": 8.75,
          "ty": -12.45,
          "a": -0.5104217529296875,
          "d": 0.5104217529296875,
          "b": 0.254852294921875,
          "c": 0.254852294921875
        }
      },
      {
        "type": "symbol",
        "name": "Symbol342",
        "transform": {
          "tx": 5.95,
          "ty": -4.9,
          "a": -0.5714263916015625,
          "d": 0.5714263916015625
        }
      },
      {
        "type": "symbol",
        "name": "Symbol411",
        "transform": {
          "tx": 2.8,
          "ty": -32.7,
          "a": -0.5714263916015625,
          "d": 0.5714263916015625
        }
      },
      {
        "type": "symbol",
        "name": "Symbol426",
        "transform": {
          "tx": -6.5,
          "ty": -1.85,
          "a": -0.5714263916015625,
          "d": 0.5714263916015625
        }
      },
      {
        "type": "symbol",
        "name": "Symbol452",
        "transform": {
          "tx": -4.85,
          "ty": -8.2,
          "a": -0.5714263916015625,
          "d": 0.5714263916015625
        }
      }
    ],
    [
      {
        "type": "symbol",
        "name": "Symbol80",
        "transform": {
          "tx": 10.15,
          "ty": -6.05,
          "a": -0.5104217529296875,
          "d": 0.5104217529296875,
          "b": 0.254852294921875,
          "c": 0.254852294921875
        }
      },
      {
        "type": "symbol",
        "name": "Symbol105",
        "transform": {
          "tx": 8.75,
          "ty": -12.45,
          "a": -0.5104217529296875,
          "d": 0.5104217529296875,
          "b": 0.254852294921875,
          "c": 0.254852294921875
        }
      },
      {
        "type": "symbol",
        "name": "Symbol342",
        "transform": {
          "tx": 5.95,
          "ty": -4.9,
          "a": -0.5714263916015625,
          "d": 0.5714263916015625
        }
      },
      {
        "type": "symbol",
        "name": "Symbol411",
        "transform": {
          "tx": 2.8,
          "ty": -32.7,
          "a": -0.5714263916015625,
          "d": 0.5714263916015625
        }
      },
      {
        "type": "symbol",
        "name": "Symbol426",
        "transform": {
          "tx": -6.5,
          "ty": -1.85,
          "a": -0.5714263916015625,
          "d": 0.5714263916015625
        }
      },
      {
        "type": "symbol",
        "name": "Symbol452",
        "transform": {
          "tx": -4.85,
          "ty": -8.2,
          "a": -0.5714263916015625,
          "d": 0.5714263916015625
        }
      }
    ],
    [
      {
        "type": "symbol",
        "name": "Symbol80",
        "transform": {
          "tx": 10.15,
          "ty": -6.05,
          "a": -0.5104217529296875,
          "d": 0.5104217529296875,
          "b": 0.254852294921875,
          "c": 0.254852294921875
        }
      },
      {
        "type": "symbol",
        "name": "Symbol105",
        "transform": {
          "tx": 8.75,
          "ty": -12.45,
          "a": -0.5104217529296875,
          "d": 0.5104217529296875,
          "b": 0.254852294921875,
          "c": 0.254852294921875
        }
      },
      {
        "type": "symbol",
        "name": "Symbol342",
        "transform": {
          "tx": 5.95,
          "ty": -4.9,
          "a": -0.5714263916015625,
          "d": 0.5714263916015625
        }
      },
      {
        "type": "symbol",
        "name": "Symbol411",
        "transform": {
          "tx": 2.8,
          "ty": -32.7,
          "a": -0.5714263916015625,
          "d": 0.5714263916015625
        }
      },
      {
        "type": "symbol",
        "name": "Symbol426",
        "transform": {
          "tx": -6.5,
          "ty": -1.85,
          "a": -0.5714263916015625,
          "d": 0.5714263916015625
        }
      },
      {
        "type": "symbol",
        "name": "Symbol452",
        "transform": {
          "tx": -4.85,
          "ty": -8.2,
          "a": -0.5714263916015625,
          "d": 0.5714263916015625
        }
      }
    ],
    [
      {
        "type": "symbol",
        "name": "Symbol80",
        "transform": {
          "tx": 10.15,
          "ty": -6.05,
          "a": -0.5104217529296875,
          "d": 0.5104217529296875,
          "b": 0.254852294921875,
          "c": 0.254852294921875
        }
      },
      {
        "type": "symbol",
        "name": "Symbol105",
        "transform": {
          "tx": 8.75,
          "ty": -12.45,
          "a": -0.5104217529296875,
          "d": 0.5104217529296875,
          "b": 0.254852294921875,
          "c": 0.254852294921875
        }
      },
      {
        "type": "symbol",
        "name": "Symbol342",
        "transform": {
          "tx": 5.95,
          "ty": -4.9,
          "a": -0.5714263916015625,
          "d": 0.5714263916015625
        }
      },
      {
        "type": "symbol",
        "name": "Symbol411",
        "transform": {
          "tx": 2.8,
          "ty": -32.7,
          "a": -0.5714263916015625,
          "d": 0.5714263916015625
        }
      },
      {
        "type": "symbol",
        "name": "Symbol426",
        "transform": {
          "tx": -6.5,
          "ty": -1.85,
          "a": -0.5714263916015625,
          "d": 0.5714263916015625
        }
      },
      {
        "type": "symbol",
        "name": "Symbol452",
        "transform": {
          "tx": -4.85,
          "ty": -8.2,
          "a": -0.5714263916015625,
          "d": 0.5714263916015625
        }
      }
    ],
    [
      {
        "type": "symbol",
        "name": "Symbol80",
        "transform": {
          "tx": 10.15,
          "ty": -6.05,
          "a": -0.5104217529296875,
          "d": 0.5104217529296875,
          "b": 0.254852294921875,
          "c": 0.254852294921875
        }
      },
      {
        "type": "symbol",
        "name": "Symbol105",
        "transform": {
          "tx": 8.75,
          "ty": -12.45,
          "a": -0.5104217529296875,
          "d": 0.5104217529296875,
          "b": 0.254852294921875,
          "c": 0.254852294921875
        }
      },
      {
        "type": "symbol",
        "name": "Symbol342",
        "transform": {
          "tx": 5.95,
          "ty": -4.9,
          "a": -0.5714263916015625,
          "d": 0.5714263916015625
        }
      },
      {
        "type": "symbol",
        "name": "Symbol411",
        "transform": {
          "tx": 2.8,
          "ty": -32.7,
          "a": -0.5714263916015625,
          "d": 0.5714263916015625
        }
      },
      {
        "type": "symbol",
        "name": "Symbol426",
        "transform": {
          "tx": -6.5,
          "ty": -1.85,
          "a": -0.5714263916015625,
          "d": 0.5714263916015625
        }
      },
      {
        "type": "symbol",
        "name": "Symbol452",
        "transform": {
          "tx": -4.85,
          "ty": -8.2,
          "a": -0.5714263916015625,
          "d": 0.5714263916015625
        }
      }
    ],
    [
      {
        "type": "symbol",
        "name": "Symbol80",
        "transform": {
          "tx": 10.15,
          "ty": -6.05,
          "a": -0.5104217529296875,
          "d": 0.5104217529296875,
          "b": 0.254852294921875,
          "c": 0.254852294921875
        }
      },
      {
        "type": "symbol",
        "name": "Symbol105",
        "transform": {
          "tx": 8.75,
          "ty": -12.45,
          "a": -0.5104217529296875,
          "d": 0.5104217529296875,
          "b": 0.254852294921875,
          "c": 0.254852294921875
        }
      },
      {
        "type": "symbol",
        "name": "Symbol342",
        "transform": {
          "tx": 5.95,
          "ty": -4.9,
          "a": -0.5714263916015625,
          "d": 0.5714263916015625
        }
      },
      {
        "type": "symbol",
        "name": "Symbol411",
        "transform": {
          "tx": 2.8,
          "ty": -32.7,
          "a": -0.5714263916015625,
          "d": 0.5714263916015625
        }
      },
      {
        "type": "symbol",
        "name": "Symbol426",
        "transform": {
          "tx": -6.5,
          "ty": -1.85,
          "a": -0.5714263916015625,
          "d": 0.5714263916015625
        }
      },
      {
        "type": "symbol",
        "name": "Symbol452",
        "transform": {
          "tx": -4.85,
          "ty": -8.2,
          "a": -0.5714263916015625,
          "d": 0.5714263916015625
        }
      }
    ],
    [
      {
        "type": "symbol",
        "name": "Symbol80",
        "transform": {
          "tx": 10.15,
          "ty": -6.05,
          "a": -0.5104217529296875,
          "d": 0.5104217529296875,
          "b": 0.254852294921875,
          "c": 0.254852294921875
        }
      },
      {
        "type": "symbol",
        "name": "Symbol105",
        "transform": {
          "tx": 8.75,
          "ty": -12.45,
          "a": -0.5104217529296875,
          "d": 0.5104217529296875,
          "b": 0.254852294921875,
          "c": 0.254852294921875
        }
      },
      {
        "type": "symbol",
        "name": "Symbol342",
        "transform": {
          "tx": 5.95,
          "ty": -4.9,
          "a": -0.5714263916015625,
          "d": 0.5714263916015625
        }
      },
      {
        "type": "symbol",
        "name": "Symbol411",
        "transform": {
          "tx": 2.8,
          "ty": -32.7,
          "a": -0.5714263916015625,
          "d": 0.5714263916015625
        }
      },
      {
        "type": "symbol",
        "name": "Symbol426",
        "transform": {
          "tx": -6.5,
          "ty": -1.85,
          "a": -0.5714263916015625,
          "d": 0.5714263916015625
        }
      },
      {
        "type": "symbol",
        "name": "Symbol452",
        "transform": {
          "tx": -4.85,
          "ty": -8.2,
          "a": -0.5714263916015625,
          "d": 0.5714263916015625
        }
      }
    ],
    [
      {
        "type": "symbol",
        "name": "Symbol80",
        "transform": {
          "tx": 10.15,
          "ty": -6.05,
          "a": -0.5104217529296875,
          "d": 0.5104217529296875,
          "b": 0.254852294921875,
          "c": 0.254852294921875
        }
      },
      {
        "type": "symbol",
        "name": "Symbol105",
        "transform": {
          "tx": 8.75,
          "ty": -12.45,
          "a": -0.5104217529296875,
          "d": 0.5104217529296875,
          "b": 0.254852294921875,
          "c": 0.254852294921875
        }
      },
      {
        "type": "symbol",
        "name": "Symbol342",
        "transform": {
          "tx": 5.95,
          "ty": -4.9,
          "a": -0.5714263916015625,
          "d": 0.5714263916015625
        }
      },
      {
        "type": "symbol",
        "name": "Symbol411",
        "transform": {
          "tx": 2.8,
          "ty": -32.7,
          "a": -0.5714263916015625,
          "d": 0.5714263916015625
        }
      },
      {
        "type": "symbol",
        "name": "Symbol426",
        "transform": {
          "tx": -6.5,
          "ty": -1.85,
          "a": -0.5714263916015625,
          "d": 0.5714263916015625
        }
      },
      {
        "type": "symbol",
        "name": "Symbol452",
        "transform": {
          "tx": -4.85,
          "ty": -8.2,
          "a": -0.5714263916015625,
          "d": 0.5714263916015625
        }
      }
    ],
    [
      {
        "type": "symbol",
        "name": "Symbol80",
        "transform": {
          "tx": 10.15,
          "ty": -6.05,
          "a": -0.5104217529296875,
          "d": 0.5104217529296875,
          "b": 0.254852294921875,
          "c": 0.254852294921875
        }
      },
      {
        "type": "symbol",
        "name": "Symbol105",
        "transform": {
          "tx": 8.75,
          "ty": -12.45,
          "a": -0.5104217529296875,
          "d": 0.5104217529296875,
          "b": 0.254852294921875,
          "c": 0.254852294921875
        }
      },
      {
        "type": "symbol",
        "name": "Symbol342",
        "transform": {
          "tx": 5.95,
          "ty": -4.9,
          "a": -0.5714263916015625,
          "d": 0.5714263916015625
        }
      },
      {
        "type": "symbol",
        "name": "Symbol411",
        "transform": {
          "tx": 2.8,
          "ty": -32.7,
          "a": -0.5714263916015625,
          "d": 0.5714263916015625
        }
      },
      {
        "type": "symbol",
        "name": "Symbol426",
        "transform": {
          "tx": -6.5,
          "ty": -1.85,
          "a": -0.5714263916015625,
          "d": 0.5714263916015625
        }
      },
      {
        "type": "symbol",
        "name": "Symbol452",
        "transform": {
          "tx": -4.85,
          "ty": -8.2,
          "a": -0.5714263916015625,
          "d": 0.5714263916015625
        }
      }
    ],
    [
      {
        "type": "symbol",
        "name": "Symbol80",
        "transform": {
          "tx": 10.15,
          "ty": -6.05,
          "a": -0.5104217529296875,
          "d": 0.5104217529296875,
          "b": 0.254852294921875,
          "c": 0.254852294921875
        }
      },
      {
        "type": "symbol",
        "name": "Symbol105",
        "transform": {
          "tx": 8.75,
          "ty": -12.45,
          "a": -0.5104217529296875,
          "d": 0.5104217529296875,
          "b": 0.254852294921875,
          "c": 0.254852294921875
        }
      },
      {
        "type": "symbol",
        "name": "Symbol342",
        "transform": {
          "tx": 5.95,
          "ty": -4.9,
          "a": -0.5714263916015625,
          "d": 0.5714263916015625
        }
      },
      {
        "type": "symbol",
        "name": "Symbol411",
        "transform": {
          "tx": 2.8,
          "ty": -32.7,
          "a": -0.5714263916015625,
          "d": 0.5714263916015625
        }
      },
      {
        "type": "symbol",
        "name": "Symbol426",
        "transform": {
          "tx": -6.5,
          "ty": -1.85,
          "a": -0.5714263916015625,
          "d": 0.5714263916015625
        }
      },
      {
        "type": "symbol",
        "name": "Symbol452",
        "transform": {
          "tx": -4.85,
          "ty": -8.2,
          "a": -0.5714263916015625,
          "d": 0.5714263916015625
        }
      }
    ],
    [
      {
        "type": "symbol",
        "name": "Symbol80",
        "transform": {
          "tx": 10.15,
          "ty": -6.05,
          "a": -0.5104217529296875,
          "d": 0.5104217529296875,
          "b": 0.254852294921875,
          "c": 0.254852294921875
        }
      },
      {
        "type": "symbol",
        "name": "Symbol105",
        "transform": {
          "tx": 8.75,
          "ty": -12.45,
          "a": -0.5104217529296875,
          "d": 0.5104217529296875,
          "b": 0.254852294921875,
          "c": 0.254852294921875
        }
      },
      {
        "type": "symbol",
        "name": "Symbol342",
        "transform": {
          "tx": 5.95,
          "ty": -4.9,
          "a": -0.5714263916015625,
          "d": 0.5714263916015625
        }
      },
      {
        "type": "symbol",
        "name": "Symbol411",
        "transform": {
          "tx": 2.8,
          "ty": -32.7,
          "a": -0.5714263916015625,
          "d": 0.5714263916015625
        }
      },
      {
        "type": "symbol",
        "name": "Symbol426",
        "transform": {
          "tx": -6.5,
          "ty": -1.85,
          "a": -0.5714263916015625,
          "d": 0.5714263916015625
        }
      },
      {
        "type": "symbol",
        "name": "Symbol452",
        "transform": {
          "tx": -4.85,
          "ty": -8.2,
          "a": -0.5714263916015625,
          "d": 0.5714263916015625
        }
      }
    ],
    [
      {
        "type": "symbol",
        "name": "Symbol80",
        "transform": {
          "tx": 10.15,
          "ty": -6.05,
          "a": -0.5104217529296875,
          "d": 0.5104217529296875,
          "b": 0.254852294921875,
          "c": 0.254852294921875
        }
      },
      {
        "type": "symbol",
        "name": "Symbol105",
        "transform": {
          "tx": 8.75,
          "ty": -12.45,
          "a": -0.5104217529296875,
          "d": 0.5104217529296875,
          "b": 0.254852294921875,
          "c": 0.254852294921875
        }
      },
      {
        "type": "symbol",
        "name": "Symbol342",
        "transform": {
          "tx": 5.95,
          "ty": -4.9,
          "a": -0.5714263916015625,
          "d": 0.5714263916015625
        }
      },
      {
        "type": "symbol",
        "name": "Symbol411",
        "transform": {
          "tx": 2.8,
          "ty": -32.7,
          "a": -0.5714263916015625,
          "d": 0.5714263916015625
        }
      },
      {
        "type": "symbol",
        "name": "Symbol426",
        "transform": {
          "tx": -6.5,
          "ty": -1.85,
          "a": -0.5714263916015625,
          "d": 0.5714263916015625
        }
      },
      {
        "type": "symbol",
        "name": "Symbol452",
        "transform": {
          "tx": -4.85,
          "ty": -8.2,
          "a": -0.5714263916015625,
          "d": 0.5714263916015625
        }
      }
    ],
    [
      {
        "type": "symbol",
        "name": "Symbol80",
        "transform": {
          "tx": 10.15,
          "ty": -6.05,
          "a": -0.5104217529296875,
          "d": 0.5104217529296875,
          "b": 0.254852294921875,
          "c": 0.254852294921875
        }
      },
      {
        "type": "symbol",
        "name": "Symbol105",
        "transform": {
          "tx": 8.75,
          "ty": -12.45,
          "a": -0.5104217529296875,
          "d": 0.5104217529296875,
          "b": 0.254852294921875,
          "c": 0.254852294921875
        }
      },
      {
        "type": "symbol",
        "name": "Symbol342",
        "transform": {
          "tx": 5.95,
          "ty": -4.9,
          "a": -0.5714263916015625,
          "d": 0.5714263916015625
        }
      },
      {
        "type": "symbol",
        "name": "Symbol411",
        "transform": {
          "tx": 2.8,
          "ty": -32.7,
          "a": -0.5714263916015625,
          "d": 0.5714263916015625
        }
      },
      {
        "type": "symbol",
        "name": "Symbol426",
        "transform": {
          "tx": -6.5,
          "ty": -1.85,
          "a": -0.5714263916015625,
          "d": 0.5714263916015625
        }
      },
      {
        "type": "symbol",
        "name": "Symbol452",
        "transform": {
          "tx": -4.85,
          "ty": -8.2,
          "a": -0.5714263916015625,
          "d": 0.5714263916015625
        }
      }
    ],
    [
      {
        "type": "symbol",
        "name": "Symbol80",
        "transform": {
          "tx": 10.15,
          "ty": -6.05,
          "a": -0.5104217529296875,
          "d": 0.5104217529296875,
          "b": 0.254852294921875,
          "c": 0.254852294921875
        }
      },
      {
        "type": "symbol",
        "name": "Symbol105",
        "transform": {
          "tx": 8.75,
          "ty": -12.45,
          "a": -0.5104217529296875,
          "d": 0.5104217529296875,
          "b": 0.254852294921875,
          "c": 0.254852294921875
        }
      },
      {
        "type": "symbol",
        "name": "Symbol342",
        "transform": {
          "tx": 5.95,
          "ty": -4.9,
          "a": -0.5714263916015625,
          "d": 0.5714263916015625
        }
      },
      {
        "type": "symbol",
        "name": "Symbol411",
        "transform": {
          "tx": 2.8,
          "ty": -32.7,
          "a": -0.5714263916015625,
          "d": 0.5714263916015625
        }
      },
      {
        "type": "symbol",
        "name": "Symbol426",
        "transform": {
          "tx": -6.5,
          "ty": -1.85,
          "a": -0.5714263916015625,
          "d": 0.5714263916015625
        }
      },
      {
        "type": "symbol",
        "name": "Symbol452",
        "transform": {
          "tx": -4.85,
          "ty": -8.2,
          "a": -0.5714263916015625,
          "d": 0.5714263916015625
        }
      }
    ],
    [
      {
        "type": "symbol",
        "name": "Symbol80",
        "transform": {
          "tx": 10.15,
          "ty": -6.05,
          "a": -0.5104217529296875,
          "d": 0.5104217529296875,
          "b": 0.254852294921875,
          "c": 0.254852294921875
        }
      },
      {
        "type": "symbol",
        "name": "Symbol105",
        "transform": {
          "tx": 8.75,
          "ty": -12.45,
          "a": -0.5104217529296875,
          "d": 0.5104217529296875,
          "b": 0.254852294921875,
          "c": 0.254852294921875
        }
      },
      {
        "type": "symbol",
        "name": "Symbol342",
        "transform": {
          "tx": 5.95,
          "ty": -4.9,
          "a": -0.5714263916015625,
          "d": 0.5714263916015625
        }
      },
      {
        "type": "symbol",
        "name": "Symbol411",
        "transform": {
          "tx": 2.8,
          "ty": -32.7,
          "a": -0.5714263916015625,
          "d": 0.5714263916015625
        }
      },
      {
        "type": "symbol",
        "name": "Symbol426",
        "transform": {
          "tx": -6.5,
          "ty": -1.85,
          "a": -0.5714263916015625,
          "d": 0.5714263916015625
        }
      },
      {
        "type": "symbol",
        "name": "Symbol452",
        "transform": {
          "tx": -4.85,
          "ty": -8.2,
          "a": -0.5714263916015625,
          "d": 0.5714263916015625
        }
      }
    ],
    [
      {
        "type": "symbol",
        "name": "Symbol80",
        "transform": {
          "tx": 10.15,
          "ty": -6.05,
          "a": -0.5104217529296875,
          "d": 0.5104217529296875,
          "b": 0.254852294921875,
          "c": 0.254852294921875
        }
      },
      {
        "type": "symbol",
        "name": "Symbol105",
        "transform": {
          "tx": 8.75,
          "ty": -12.45,
          "a": -0.5104217529296875,
          "d": 0.5104217529296875,
          "b": 0.254852294921875,
          "c": 0.254852294921875
        }
      },
      {
        "type": "symbol",
        "name": "Symbol342",
        "transform": {
          "tx": 5.95,
          "ty": -4.9,
          "a": -0.5714263916015625,
          "d": 0.5714263916015625
        }
      },
      {
        "type": "symbol",
        "name": "Symbol411",
        "transform": {
          "tx": 2.8,
          "ty": -32.7,
          "a": -0.5714263916015625,
          "d": 0.5714263916015625
        }
      },
      {
        "type": "symbol",
        "name": "Symbol426",
        "transform": {
          "tx": -6.5,
          "ty": -1.85,
          "a": -0.5714263916015625,
          "d": 0.5714263916015625
        }
      },
      {
        "type": "symbol",
        "name": "Symbol452",
        "transform": {
          "tx": -4.85,
          "ty": -8.2,
          "a": -0.5714263916015625,
          "d": 0.5714263916015625
        }
      }
    ],
    [
      {
        "type": "symbol",
        "name": "Symbol80",
        "transform": {
          "tx": 10.15,
          "ty": -6.05,
          "a": -0.5104217529296875,
          "d": 0.5104217529296875,
          "b": 0.254852294921875,
          "c": 0.254852294921875
        }
      },
      {
        "type": "symbol",
        "name": "Symbol105",
        "transform": {
          "tx": 8.75,
          "ty": -12.45,
          "a": -0.5104217529296875,
          "d": 0.5104217529296875,
          "b": 0.254852294921875,
          "c": 0.254852294921875
        }
      },
      {
        "type": "symbol",
        "name": "Symbol342",
        "transform": {
          "tx": 5.95,
          "ty": -4.9,
          "a": -0.5714263916015625,
          "d": 0.5714263916015625
        }
      },
      {
        "type": "symbol",
        "name": "Symbol411",
        "transform": {
          "tx": 2.8,
          "ty": -32.7,
          "a": -0.5714263916015625,
          "d": 0.5714263916015625
        }
      },
      {
        "type": "symbol",
        "name": "Symbol426",
        "transform": {
          "tx": -6.5,
          "ty": -1.85,
          "a": -0.5714263916015625,
          "d": 0.5714263916015625
        }
      },
      {
        "type": "symbol",
        "name": "Symbol452",
        "transform": {
          "tx": -4.85,
          "ty": -8.2,
          "a": -0.5714263916015625,
          "d": 0.5714263916015625
        }
      }
    ],
    [
      {
        "type": "symbol",
        "name": "Symbol80",
        "transform": {
          "tx": 10.15,
          "ty": -6.05,
          "a": -0.5104217529296875,
          "d": 0.5104217529296875,
          "b": 0.254852294921875,
          "c": 0.254852294921875
        }
      },
      {
        "type": "symbol",
        "name": "Symbol105",
        "transform": {
          "tx": 8.75,
          "ty": -12.45,
          "a": -0.5104217529296875,
          "d": 0.5104217529296875,
          "b": 0.254852294921875,
          "c": 0.254852294921875
        }
      },
      {
        "type": "symbol",
        "name": "Symbol342",
        "transform": {
          "tx": 5.95,
          "ty": -4.9,
          "a": -0.5714263916015625,
          "d": 0.5714263916015625
        }
      },
      {
        "type": "symbol",
        "name": "Symbol411",
        "transform": {
          "tx": 2.8,
          "ty": -32.7,
          "a": -0.5714263916015625,
          "d": 0.5714263916015625
        }
      },
      {
        "type": "symbol",
        "name": "Symbol426",
        "transform": {
          "tx": -6.5,
          "ty": -1.85,
          "a": -0.5714263916015625,
          "d": 0.5714263916015625
        }
      },
      {
        "type": "symbol",
        "name": "Symbol452",
        "transform": {
          "tx": -4.85,
          "ty": -8.2,
          "a": -0.5714263916015625,
          "d": 0.5714263916015625
        }
      }
    ],
    [
      {
        "type": "symbol",
        "name": "Symbol80",
        "transform": {
          "tx": 10.15,
          "ty": -6.05,
          "a": -0.5104217529296875,
          "d": 0.5104217529296875,
          "b": 0.254852294921875,
          "c": 0.254852294921875
        }
      },
      {
        "type": "symbol",
        "name": "Symbol105",
        "transform": {
          "tx": 8.75,
          "ty": -12.45,
          "a": -0.5104217529296875,
          "d": 0.5104217529296875,
          "b": 0.254852294921875,
          "c": 0.254852294921875
        }
      },
      {
        "type": "symbol",
        "name": "Symbol342",
        "transform": {
          "tx": 5.95,
          "ty": -4.9,
          "a": -0.5714263916015625,
          "d": 0.5714263916015625
        }
      },
      {
        "type": "symbol",
        "name": "Symbol411",
        "transform": {
          "tx": 2.8,
          "ty": -32.7,
          "a": -0.5714263916015625,
          "d": 0.5714263916015625
        }
      },
      {
        "type": "symbol",
        "name": "Symbol426",
        "transform": {
          "tx": -6.5,
          "ty": -1.85,
          "a": -0.5714263916015625,
          "d": 0.5714263916015625
        }
      },
      {
        "type": "symbol",
        "name": "Symbol452",
        "transform": {
          "tx": -4.85,
          "ty": -8.2,
          "a": -0.5714263916015625,
          "d": 0.5714263916015625
        }
      }
    ],
    [
      {
        "type": "symbol",
        "name": "Symbol80",
        "transform": {
          "tx": 10.15,
          "ty": -6.05,
          "a": -0.5104217529296875,
          "d": 0.5104217529296875,
          "b": 0.254852294921875,
          "c": 0.254852294921875
        }
      },
      {
        "type": "symbol",
        "name": "Symbol105",
        "transform": {
          "tx": 8.75,
          "ty": -12.45,
          "a": -0.5104217529296875,
          "d": 0.5104217529296875,
          "b": 0.254852294921875,
          "c": 0.254852294921875
        }
      },
      {
        "type": "symbol",
        "name": "Symbol342",
        "transform": {
          "tx": 5.95,
          "ty": -4.9,
          "a": -0.5714263916015625,
          "d": 0.5714263916015625
        }
      },
      {
        "type": "symbol",
        "name": "Symbol411",
        "transform": {
          "tx": 2.8,
          "ty": -32.7,
          "a": -0.5714263916015625,
          "d": 0.5714263916015625
        }
      },
      {
        "type": "symbol",
        "name": "Symbol426",
        "transform": {
          "tx": -6.5,
          "ty": -1.85,
          "a": -0.5714263916015625,
          "d": 0.5714263916015625
        }
      },
      {
        "type": "symbol",
        "name": "Symbol452",
        "transform": {
          "tx": -4.85,
          "ty": -8.2,
          "a": -0.5714263916015625,
          "d": 0.5714263916015625
        }
      }
    ],
    [
      {
        "type": "symbol",
        "name": "Symbol80",
        "transform": {
          "tx": 10.15,
          "ty": -6.05,
          "a": -0.5104217529296875,
          "d": 0.5104217529296875,
          "b": 0.254852294921875,
          "c": 0.254852294921875
        }
      },
      {
        "type": "symbol",
        "name": "Symbol105",
        "transform": {
          "tx": 8.75,
          "ty": -12.45,
          "a": -0.5104217529296875,
          "d": 0.5104217529296875,
          "b": 0.254852294921875,
          "c": 0.254852294921875
        }
      },
      {
        "type": "symbol",
        "name": "Symbol342",
        "transform": {
          "tx": 5.95,
          "ty": -4.9,
          "a": -0.5714263916015625,
          "d": 0.5714263916015625
        }
      },
      {
        "type": "symbol",
        "name": "Symbol411",
        "transform": {
          "tx": 2.8,
          "ty": -32.7,
          "a": -0.5714263916015625,
          "d": 0.5714263916015625
        }
      },
      {
        "type": "symbol",
        "name": "Symbol426",
        "transform": {
          "tx": -6.5,
          "ty": -1.85,
          "a": -0.5714263916015625,
          "d": 0.5714263916015625
        }
      },
      {
        "type": "symbol",
        "name": "Symbol452",
        "transform": {
          "tx": -4.85,
          "ty": -8.2,
          "a": -0.5714263916015625,
          "d": 0.5714263916015625
        }
      }
    ],
    [
      {
        "type": "symbol",
        "name": "Symbol80",
        "transform": {
          "tx": 10.15,
          "ty": -6.05,
          "a": -0.5104217529296875,
          "d": 0.5104217529296875,
          "b": 0.254852294921875,
          "c": 0.254852294921875
        }
      },
      {
        "type": "symbol",
        "name": "Symbol105",
        "transform": {
          "tx": 8.75,
          "ty": -12.45,
          "a": -0.5104217529296875,
          "d": 0.5104217529296875,
          "b": 0.254852294921875,
          "c": 0.254852294921875
        }
      },
      {
        "type": "symbol",
        "name": "Symbol342",
        "transform": {
          "tx": 5.95,
          "ty": -4.9,
          "a": -0.5714263916015625,
          "d": 0.5714263916015625
        }
      },
      {
        "type": "symbol",
        "name": "Symbol411",
        "transform": {
          "tx": 2.8,
          "ty": -32.7,
          "a": -0.5714263916015625,
          "d": 0.5714263916015625
        }
      },
      {
        "type": "symbol",
        "name": "Symbol426",
        "transform": {
          "tx": -6.5,
          "ty": -1.85,
          "a": -0.5714263916015625,
          "d": 0.5714263916015625
        }
      },
      {
        "type": "symbol",
        "name": "Symbol452",
        "transform": {
          "tx": -4.85,
          "ty": -8.2,
          "a": -0.5714263916015625,
          "d": 0.5714263916015625
        }
      }
    ],
    [
      {
        "type": "symbol",
        "name": "Symbol80",
        "transform": {
          "tx": 10.15,
          "ty": -6.05,
          "a": -0.5104217529296875,
          "d": 0.5104217529296875,
          "b": 0.254852294921875,
          "c": 0.254852294921875
        }
      },
      {
        "type": "symbol",
        "name": "Symbol105",
        "transform": {
          "tx": 8.75,
          "ty": -12.45,
          "a": -0.5104217529296875,
          "d": 0.5104217529296875,
          "b": 0.254852294921875,
          "c": 0.254852294921875
        }
      },
      {
        "type": "symbol",
        "name": "Symbol342",
        "transform": {
          "tx": 5.95,
          "ty": -4.9,
          "a": -0.5714263916015625,
          "d": 0.5714263916015625
        }
      },
      {
        "type": "symbol",
        "name": "Symbol411",
        "transform": {
          "tx": 2.8,
          "ty": -32.7,
          "a": -0.5714263916015625,
          "d": 0.5714263916015625
        }
      },
      {
        "type": "symbol",
        "name": "Symbol426",
        "transform": {
          "tx": -6.5,
          "ty": -1.85,
          "a": -0.5714263916015625,
          "d": 0.5714263916015625
        }
      },
      {
        "type": "symbol",
        "name": "Symbol452",
        "transform": {
          "tx": -4.85,
          "ty": -8.2,
          "a": -0.5714263916015625,
          "d": 0.5714263916015625
        }
      }
    ]
  ]
}