{
  "name": "Symbol911",
  "layers": [
    {
      "frames": [
        {
          "parts": [
            {
              "name": "REPLACE|Symbol885|REPLACE",
              "layers": [],
              "type": "symbol",
              "colorOffset": {
                "r": -72,
                "g": -148,
                "b": -215
              },
              "transform": {
                "tx": -3.65,
                "ty": 0.4,
                "a": 2.2337493896484375,
                "d": 1.624176025390625,
                "b": -1.5350189208984375,
                "c": 1.11614990234375
              }
            }
          ]
        },
        {
          "parts": [
            {
              "name": "REPLACE|Symbol885|REPLACE",
              "layers": [],
              "type": "symbol",
              "colorOffset": {
                "r": -72,
                "g": -148,
                "b": -215
              },
              "transform": {
                "tx": -3.35,
                "ty": -1.35,
                "a": 2.6203155517578125,
                "d": 1.9052886962890625,
                "b": -0.6684722900390625,
                "c": 0.486083984375
              }
            }
          ]
        },
        {
          "parts": [
            {
              "name": "REPLACE|Symbol885|REPLACE",
              "layers": [],
              "type": "symbol",
              "colorOffset": {
                "r": -72,
                "g": -148,
                "b": -215
              },
              "transform": {
                "tx": -3.05,
                "ty": -2.9,
                "a": 2.6896514892578125,
                "d": 1.9556732177734375,
                "b": 0.2637481689453125,
                "c": -0.191741943359375
              }
            }
          ]
        }
      ]
    },
    {
      "frames": [
        {
          "parts": [
            {
              "name": "REPLACE|Symbol885|REPLACE",
              "layers": [],
              "type": "symbol",
              "colorOffset": {
                "r": -72,
                "g": -148,
                "b": -215
              },
              "transform": {
                "tx": -2.55,
                "ty": 10.5,
                "a": 2.081512451171875,
                "d": 2.081512451171875,
                "b": 0.835296630859375,
                "c": -0.83526611328125
              }
            }
          ]
        },
        {
          "parts": [
            {
              "name": "REPLACE|Symbol885|REPLACE",
              "layers": [],
              "type": "symbol",
              "colorOffset": {
                "r": -72,
                "g": -148,
                "b": -215
              },
              "transform": {
                "tx": -3.5,
                "ty": 8.3,
                "a": 2.183319091796875,
                "d": 2.18328857421875,
                "b": 0.496612548828125,
                "c": -0.4966583251953125
              }
            }
          ]
        },
        {
          "parts": [
            {
              "name": "REPLACE|Symbol885|REPLACE",
              "layers": [],
              "type": "symbol",
              "colorOffset": {
                "r": -72,
                "g": -148,
                "b": -215
              },
              "transform": {
                "tx": -4.35,
                "ty": 6.1,
                "a": 2.23291015625,
                "d": 2.2328948974609375,
                "b": 0.1593475341796875,
                "c": -0.1593170166015625
              }
            }
          ]
        }
      ]
    },
    {
      "frames": [
        {
          "parts": [
            {
              "name": "REPLACE|Symbol889|REPLACE",
              "layers": [],
              "type": "symbol",
              "colorOffset": {
                "r": -72,
                "g": -148,
                "b": -215
              },
              "transform": {
                "tx": 6.55,
                "ty": -1.3,
                "a": 1.242034912109375,
                "d": 1.242034912109375,
                "b": -0.78387451171875,
                "c": 0.78387451171875
              }
            }
          ]
        },
        {
          "parts": [
            {
              "name": "REPLACE|Symbol889|REPLACE",
              "layers": [],
              "type": "symbol",
              "colorOffset": {
                "r": -72,
                "g": -148,
                "b": -215
              },
              "transform": {
                "tx": 7.4,
                "ty": -2.7,
                "a": 1.427001953125,
                "d": 1.427001953125,
                "b": -0.3368682861328125,
                "c": 0.3368682861328125
              }
            }
          ]
        },
        {
          "parts": [
            {
              "name": "REPLACE|Symbol889|REPLACE",
              "layers": [],
              "type": "symbol",
              "colorOffset": {
                "r": -72,
                "g": -148,
                "b": -215
              },
              "transform": {
                "tx": 8.1,
                "ty": -4.05,
                "a": 1.4589691162109375,
                "d": 1.4589691162109375,
                "b": 0.142333984375,
                "c": -0.142333984375
              }
            }
          ]
        }
      ]
    },
    {
      "frames": [
        {
          "parts": [
            {
              "name": "REPLACE|Symbol885|REPLACE",
              "layers": [],
              "type": "symbol",
              "colorOffset": {
                "r": -72,
                "g": -148,
                "b": -215
              },
              "transform": {
                "tx": 9.6,
                "ty": 4.75,
                "a": 1.8359527587890625,
                "d": 1.8359527587890625,
                "b": 0.0258941650390625,
                "c": -0.0258941650390625
              }
            }
          ]
        },
        {
          "parts": [
            {
              "name": "REPLACE|Symbol885|REPLACE",
              "layers": [],
              "type": "symbol",
              "colorOffset": {
                "r": -72,
                "g": -148,
                "b": -215
              },
              "transform": {
                "tx": 8.5,
                "ty": 4.9,
                "a": 1.8330841064453125,
                "d": 1.8330841064453125,
                "b": -0.0726165771484375,
                "c": 0.0726165771484375
              }
            }
          ]
        },
        {
          "parts": [
            {
              "name": "REPLACE|Symbol885|REPLACE",
              "layers": [],
              "type": "symbol",
              "colorOffset": {
                "r": -72,
                "g": -148,
                "b": -215
              },
              "transform": {
                "tx": 7.4,
                "ty": 5.1,
                "a": 1.8251953125,
                "d": 1.8251953125,
                "b": -0.17431640625,
                "c": 0.17431640625
              }
            }
          ]
        }
      ]
    },
    {
      "frames": [
        {
          "parts": [
            {
              "name": "REPLACE|Symbol893|REPLACE",
              "layers": [],
              "type": "symbol",
              "colorOffset": {
                "r": -72,
                "g": -148,
                "b": -215
              },
              "transform": {
                "tx": -16.3,
                "ty": -0.35,
                "a": 1.3595428466796875,
                "d": 1.3595428466796875,
                "b": -0.1926116943359375,
                "c": 0.1926116943359375
              }
            }
          ]
        },
        {
          "parts": [
            {
              "name": "REPLACE|Symbol893|REPLACE",
              "layers": [],
              "type": "symbol",
              "colorOffset": {
                "r": -72,
                "g": -148,
                "b": -215
              },
              "transform": {
                "tx": -15.05,
                "ty": -1.35,
                "a": 1.2825927734375,
                "d": 1.2825927734375,
                "b": -0.4815673828125,
                "c": 0.4815673828125
              }
            }
          ]
        },
        {
          "parts": [
            {
              "name": "REPLACE|Symbol893|REPLACE",
              "layers": [],
              "type": "symbol",
              "colorOffset": {
                "r": -72,
                "g": -148,
                "b": -215
              },
              "transform": {
                "tx": -13.75,
                "ty": -2.25,
                "a": 1.1438140869140625,
                "d": 1.1438140869140625,
                "b": -0.753814697265625,
                "c": 0.753814697265625
              }
            }
          ]
        }
      ]
    },
    {
      "frames": [
        {
          "parts": [
            {
              "name": "REPLACE|Symbol883|REPLACE",
              "layers": [],
              "type": "symbol",
              "colorOffset": {
                "r": -72,
                "g": -148,
                "b": -215
              },
              "transform": {
                "tx": -8.1,
                "ty": 17.05,
                "a": 1.389007568359375,
                "d": 1.389007568359375
              }
            }
          ]
        },
        {
          "parts": [
            {
              "name": "REPLACE|Symbol883|REPLACE",
              "layers": [],
              "type": "symbol",
              "colorOffset": {
                "r": -72,
                "g": -148,
                "b": -215
              },
              "transform": {
                "tx": -7.45,
                "ty": 15.9,
                "a": 1.2328643798828125,
                "d": 1.2328643798828125,
                "b": -0.6305999755859375,
                "c": 0.6305999755859375
              }
            }
          ]
        },
        {
          "parts": [
            {
              "name": "REPLACE|Symbol883|REPLACE",
              "layers": [],
              "type": "symbol",
              "colorOffset": {
                "r": -72,
                "g": -148,
                "b": -215
              },
              "transform": {
                "tx": -6.85,
                "ty": 14.6,
                "a": 0.805755615234375,
                "d": 0.805755615234375,
                "b": -1.1255035400390625,
                "c": 1.1255035400390625
              }
            }
          ]
        }
      ]
    },
    {
      "frames": [
        {
          "parts": [
            {
              "name": "REPLACE|Symbol883|REPLACE",
              "layers": [],
              "type": "symbol",
              "colorOffset": {
                "r": -72,
                "g": -148,
                "b": -215
              },
              "transform": {
                "tx": 7.8,
                "ty": 11.2,
                "a": 0.8669891357421875,
                "d": 1.13671875
              }
            }
          ]
        },
        {
          "parts": [
            {
              "name": "REPLACE|Symbol883|REPLACE",
              "layers": [],
              "type": "symbol",
              "colorOffset": {
                "r": -72,
                "g": -148,
                "b": -215
              },
              "transform": {
                "tx": 7.2,
                "ty": 11.65,
                "a": 0.7421417236328125,
                "d": 0.9730377197265625,
                "b": -0.4433441162109375,
                "c": 0.5812530517578125
              }
            }
          ]
        },
        {
          "parts": [
            {
              "name": "REPLACE|Symbol883|REPLACE",
              "layers": [],
              "type": "symbol",
              "colorOffset": {
                "r": -72,
                "g": -148,
                "b": -215
              },
              "transform": {
                "tx": 6.55,
                "ty": 12.1,
                "a": 0.40679931640625,
                "d": 0.5333709716796875,
                "b": -0.7627410888671875,
                "c": 1.0000152587890625
              }
            }
          ]
        }
      ]
    },
    {
      "frames": [
        {
          "parts": [
            {
              "name": "REPLACE|Symbol891|REPLACE",
              "layers": [],
              "type": "symbol",
              "colorOffset": {
                "r": -72,
                "g": -148,
                "b": -215
              },
              "transform": {
                "tx": -5.5,
                "ty": -0.45,
                "a": 2.0252685546875,
                "d": 2.4904937744140625
              }
            }
          ]
        },
        {
          "parts": [
            {
              "name": "REPLACE|Symbol891|REPLACE",
              "layers": [],
              "type": "symbol",
              "colorOffset": {
                "r": -72,
                "g": -148,
                "b": -215
              },
              "transform": {
                "tx": -4.35,
                "ty": -3.05,
                "a": 2.0170440673828125,
                "d": 2.4803924560546875,
                "b": 0.16888427734375,
                "c": -0.2076873779296875
              }
            }
          ]
        },
        {
          "parts": [
            {
              "name": "REPLACE|Symbol891|REPLACE",
              "layers": [],
              "type": "symbol",
              "colorOffset": {
                "r": -72,
                "g": -148,
                "b": -215
              },
              "transform": {
                "tx": -3.1,
                "ty": -5.75,
                "a": 1.9947357177734375,
                "d": 2.45294189453125,
                "b": 0.3437652587890625,
                "c": -0.4227294921875
              }
            }
          ]
        }
      ]
    },
    {
      "frames": [
        {
          "parts": [
            {
              "name": "REPLACE|Symbol891|REPLACE",
              "layers": [],
              "type": "symbol",
              "colorOffset": {
                "r": -72,
                "g": -148,
                "b": -215
              },
              "transform": {
                "tx": 3.8,
                "ty": -4.65,
                "a": -1.24835205078125,
                "d": 1.24835205078125,
                "b": 0.5897216796875,
                "c": 0.5897216796875
              }
            }
          ]
        },
        {
          "parts": [
            {
              "name": "REPLACE|Symbol891|REPLACE",
              "layers": [],
              "type": "symbol",
              "colorOffset": {
                "r": -72,
                "g": -148,
                "b": -215
              },
              "transform": {
                "tx": 5.25,
                "ty": -5.5,
                "a": -1.37298583984375,
                "d": 1.37298583984375,
                "b": 0.12677001953125,
                "c": 0.12677001953125
              }
            }
          ]
        },
        {
          "parts": [
            {
              "name": "REPLACE|Symbol891|REPLACE",
              "layers": [],
              "type": "symbol",
              "colorOffset": {
                "r": -72,
                "g": -148,
                "b": -215
              },
              "transform": {
                "tx": 6.8,
                "ty": -6.35,
                "a": -1.333404541015625,
                "d": 1.333404541015625,
                "b": -0.3473358154296875,
                "c": -0.3473358154296875
              }
            }
          ]
        }
      ]
    },
    {
      "frames": [
        {
          "parts": [
            {
              "name": "REPLACE|Symbol885|REPLACE",
              "layers": [],
              "type": "symbol",
              "colorOffset": {
                "r": -72,
                "g": -148,
                "b": -215
              },
              "transform": {
                "tx": 1.55,
                "ty": 2.4,
                "a": 1.76666259765625,
                "d": 1.53167724609375,
                "b": 0.43365478515625,
                "c": -0.5001983642578125
              }
            }
          ]
        },
        {
          "parts": [
            {
              "name": "REPLACE|Symbol885|REPLACE",
              "layers": [],
              "type": "symbol",
              "colorOffset": {
                "r": -72,
                "g": -148,
                "b": -215
              },
              "transform": {
                "tx": 2.5,
                "ty": 2,
                "a": 1.8166961669921875,
                "d": 1.6070098876953125,
                "b": -0.0336761474609375,
                "c": -0.084564208984375
              }
            }
          ]
        },
        {
          "parts": [
            {
              "name": "REPLACE|Symbol885|REPLACE",
              "layers": [],
              "type": "symbol",
              "colorOffset": {
                "r": -72,
                "g": -148,
                "b": -215
              },
              "transform": {
                "tx": 3.4,
                "ty": 1.6,
                "a": 1.742401123046875,
                "d": 1.5727386474609375,
                "b": -0.50885009765625,
                "c": 0.3339080810546875
              }
            }
          ]
        }
      ]
    },
    {
      "frames": [
        {
          "parts": [
            {
              "name": "REPLACE|Symbol889|REPLACE",
              "layers": [],
              "type": "symbol",
              "colorOffset": {
                "r": -72,
                "g": -148,
                "b": -215
              },
              "transform": {
                "tx": 2.15,
                "ty": -3.95,
                "a": 1.467559814453125,
                "d": 1.2723541259765625,
                "b": -0.050140380859375,
                "c": 0.0578460693359375
              }
            }
          ]
        },
        {
          "parts": [
            {
              "name": "REPLACE|Symbol889|REPLACE",
              "layers": [],
              "type": "symbol",
              "colorOffset": {
                "r": -72,
                "g": -148,
                "b": -215
              },
              "transform": {
                "tx": 3.65,
                "ty": -5.9,
                "a": 1.4660186767578125,
                "d": 1.2721405029296875,
                "b": 0.0715789794921875,
                "c": -0.0501861572265625
              }
            }
          ]
        },
        {
          "parts": [
            {
              "name": "REPLACE|Symbol889|REPLACE",
              "layers": [],
              "type": "symbol",
              "colorOffset": {
                "r": -72,
                "g": -148,
                "b": -215
              },
              "transform": {
                "tx": 5,
                "ty": -7.9,
                "a": 1.453948974609375,
                "d": 1.2629852294921875,
                "b": 0.1997222900390625,
                "c": -0.15899658203125
              }
            }
          ]
        }
      ]
    },
    {
      "frames": [
        {
          "parts": [
            {
              "name": "REPLACE|Symbol883|REPLACE",
              "layers": [],
              "type": "symbol",
              "colorOffset": {
                "r": -72,
                "g": -148,
                "b": -215
              },
              "transform": {
                "tx": -2.65,
                "ty": 7.2,
                "a": 1.13671875,
                "d": 0.9855194091796875
              }
            }
          ]
        },
        {
          "parts": [
            {
              "name": "REPLACE|Symbol883|REPLACE",
              "layers": [],
              "type": "symbol",
              "colorOffset": {
                "r": -72,
                "g": -148,
                "b": -215
              },
              "transform": {
                "tx": 0.05,
                "ty": 7.75,
                "a": 0.983123779296875,
                "d": 0.85235595703125,
                "b": -0.5633392333984375,
                "c": 0.4884185791015625
              }
            }
          ]
        },
        {
          "parts": [
            {
              "name": "REPLACE|Symbol883|REPLACE",
              "layers": [],
              "type": "symbol",
              "colorOffset": {
                "r": -72,
                "g": -148,
                "b": -215
              },
              "transform": {
                "tx": 2.7,
                "ty": 8.3,
                "a": 0.5725860595703125,
                "d": 0.4964141845703125,
                "b": -0.9772796630859375,
                "c": 0.8472747802734375
              }
            }
          ]
        }
      ]
    },
    {
      "frames": [
        {
          "parts": [
            {
              "name": "REPLACE|Symbol887|REPLACE",
              "layers": [],
              "type": "symbol",
              "colorOffset": {
                "r": -72,
                "g": -148,
                "b": -215
              },
              "transform": {
                "tx": 12.3,
                "ty": -1.3,
                "a": 0.7757110595703125,
                "d": 0.7757110595703125,
                "b": 0.8283538818359375,
                "c": -0.8283538818359375
              }
            }
          ]
        },
        {
          "parts": [
            {
              "name": "REPLACE|Symbol887|REPLACE",
              "layers": [],
              "type": "symbol",
              "colorOffset": {
                "r": -72,
                "g": -148,
                "b": -215
              },
              "transform": {
                "tx": 13.45,
                "ty": -0.3,
                "a": 0.6994171142578125,
                "d": 0.6994171142578125,
                "b": 0.8910369873046875,
                "c": -0.8910369873046875
              }
            }
          ]
        },
        {
          "parts": [
            {
              "name": "REPLACE|Symbol887|REPLACE",
              "layers": [],
              "type": "symbol",
              "colorOffset": {
                "r": -72,
                "g": -148,
                "b": -215
              },
              "transform": {
                "tx": 14.55,
                "ty": 0.8,
                "a": 0.6234130859375,
                "d": 0.6234130859375,
                "b": 0.947540283203125,
                "c": -0.947540283203125
              }
            }
          ]
        }
      ]
    },
    {
      "frames": [
        {
          "parts": [
            {
              "name": "REPLACE|Symbol885|REPLACE",
              "layers": [],
              "type": "symbol",
              "colorOffset": {
                "r": -72,
                "g": -148,
                "b": -215
              },
              "transform": {
                "tx": -9.85,
                "ty": -1.35,
                "a": 2.04498291015625,
                "d": 1.34783935546875,
                "b": -1.2738494873046875,
                "c": 1.0218353271484375
              }
            }
          ]
        },
        {
          "parts": [
            {
              "name": "REPLACE|Symbol885|REPLACE",
              "layers": [],
              "type": "symbol",
              "colorOffset": {
                "r": -72,
                "g": -148,
                "b": -215
              },
              "transform": {
                "tx": -8.45,
                "ty": -4.4,
                "a": 2.1422576904296875,
                "d": 1.4269866943359375,
                "b": -1.0937347412109375,
                "c": 0.902496337890625
              }
            }
          ]
        },
        {
          "parts": [
            {
              "name": "REPLACE|Symbol885|REPLACE",
              "layers": [],
              "type": "symbol",
              "colorOffset": {
                "r": -72,
                "g": -148,
                "b": -215
              },
              "transform": {
                "tx": -7.25,
                "ty": -7.4,
                "a": 2.230377197265625,
                "d": 1.5009613037109375,
                "b": -0.90753173828125,
                "c": 0.77764892578125
              }
            }
          ]
        }
      ]
    },
    {
      "frames": [
        {
          "parts": [
            {
              "name": "REPLACE|Symbol885|REPLACE",
              "layers": [],
              "type": "symbol",
              "colorOffset": {
                "r": -72,
                "g": -148,
                "b": -215
              },
              "transform": {
                "tx": -9.35,
                "ty": 5,
                "a": 1.7642059326171875,
                "d": 1.59918212890625,
                "b": 0.95361328125,
                "c": -1.0519866943359375
              }
            }
          ]
        },
        {
          "parts": [
            {
              "name": "REPLACE|Symbol885|REPLACE",
              "layers": [],
              "type": "symbol",
              "colorOffset": {
                "r": -72,
                "g": -148,
                "b": -215
              },
              "transform": {
                "tx": -9.4,
                "ty": 3.55,
                "a": 1.92333984375,
                "d": 1.78240966796875,
                "b": 0.55413818359375,
                "c": -0.6866607666015625
              }
            }
          ]
        },
        {
          "parts": [
            {
              "name": "REPLACE|Symbol885|REPLACE",
              "layers": [],
              "type": "symbol",
              "colorOffset": {
                "r": -72,
                "g": -148,
                "b": -215
              },
              "transform": {
                "tx": -9.5,
                "ty": 2.1,
                "a": 1.9962615966796875,
                "d": 1.886627197265625,
                "b": 0.141937255859375,
                "c": -0.299224853515625
              }
            }
          ]
        }
      ]
    },
    {
      "frames": [
        {
          "parts": [
            {
              "name": "REPLACE|Symbol883|REPLACE",
              "layers": [],
              "type": "symbol",
              "colorOffset": {
                "r": -72,
                "g": -148,
                "b": -215
              },
              "transform": {
                "tx": -14.8,
                "ty": 10.45,
                "a": 1.271636962890625,
                "d": 1.1526947021484375
              }
            }
          ]
        },
        {
          "parts": [
            {
              "name": "REPLACE|Symbol883|REPLACE",
              "layers": [],
              "type": "symbol",
              "colorOffset": {
                "r": -72,
                "g": -148,
                "b": -215
              },
              "transform": {
                "tx": -13.25,
                "ty": 10.05,
                "a": 1.12353515625,
                "d": 1.0184173583984375,
                "b": -0.5871734619140625,
                "c": 0.532257080078125
              }
            }
          ]
        },
        {
          "parts": [
            {
              "name": "REPLACE|Symbol883|REPLACE",
              "layers": [],
              "type": "symbol",
              "colorOffset": {
                "r": -72,
                "g": -148,
                "b": -215
              },
              "transform": {
                "tx": -11.8,
                "ty": 9.55,
                "a": 0.7192535400390625,
                "d": 0.6519622802734375,
                "b": -1.04327392578125,
                "c": 0.9456634521484375
              }
            }
          ]
        }
      ]
    }
  ],
  "type": "symbol"
}