{
  "name": "Symbol862",
  "layers": [
    {
      "frames": [
        {
          "parts": [
            {
              "name": "REPLACE|Symbol834|REPLACE",
              "layers": [],
              "type": "symbol",
              "transform": {
                "tx": -1.9,
                "ty": -6.9,
                "a": -0.4903564453125,
                "d": 0.4903564453125,
                "b": -0.1313934326171875,
                "c": -0.1313934326171875
              }
            }
          ]
        }
      ]
    },
    {
      "frames": [
        {
          "parts": [
            {
              "name": "REPLACE|Symbol821|REPLACE",
              "layers": [],
              "type": "symbol",
              "transform": {
                "tx": -4.9,
                "ty": -1.55,
                "a": -0.5915679931640625,
                "d": 0.5915679931640625,
                "b": -0.145050048828125,
                "c": -0.145050048828125
              }
            }
          ]
        }
      ]
    },
    {
      "frames": [
        {
          "parts": [
            {
              "name": "REPLACE|Symbol807|REPLACE",
              "layers": [],
              "type": "symbol",
              "transform": {
                "tx": 3.45,
                "ty": -33.85,
                "a": -0.6100311279296875,
                "d": 0.6100311279296875
              }
            }
          ]
        }
      ]
    },
    {
      "frames": [
        {
          "parts": [
            {
              "name": "REPLACE|Symbol773|REPLACE",
              "layers": [],
              "type": "symbol",
              "transform": {
                "tx": 6.2,
                "ty": -3.55,
                "a": -0.56817626953125,
                "d": 0.51483154296875,
                "b": 0,
                "c": 0.06134033203125
              }
            }
          ]
        }
      ]
    },
    {
      "frames": [
        {
          "parts": [
            {
              "name": "REPLACE|Symbol594|REPLACE",
              "layers": [],
              "type": "symbol",
              "transform": {
                "tx": 8.5,
                "ty": -9.6,
                "a": -0.39892578125,
                "d": 0.39892578125,
                "b": 0.309814453125,
                "c": 0.309814453125
              }
            }
          ]
        }
      ]
    },
    {
      "frames": [
        {
          "parts": [
            {
              "name": "REPLACE|Symbol581|REPLACE",
              "layers": [],
              "type": "symbol",
              "transform": {
                "tx": 12.15,
                "ty": -2.5,
                "a": -0.435028076171875,
                "d": 0.435028076171875,
                "b": 0.425384521484375,
                "c": 0.425384521484375
              }
            }
          ]
        }
      ]
    },
    {
      "frames": [
        {
          "parts": [
            {
              "name": "REPLACE|Symbol563|REPLACE",
              "layers": [],
              "type": "symbol",
              "transform": {
                "tx": -7.65,
                "ty": -6.5,
                "a": -0.6100311279296875,
                "d": 0.6100311279296875
              }
            }
          ]
        }
      ]
    }
  ],
  "type": "symbol"
}