{
  "name": "Symbol115",
  "layers": [
    {
      "frames": [
        {
          "parts": [
            {
              "name": "REPLACE|Symbol114|REPLACE",
              "layers": [],
              "transform": {
                "tx": 0,
                "ty": 0
              }
            }
          ]
        }
      ]
    },
    {
      "frames": [
        {
          "parts": [
            {
              "name": "REPLACE|Symbol113|REPLACE",
              "layers": [],
              "partIdx": 3,
              "transform": {
                "tx": 5,
                "ty": 3.15
              }
            }
          ]
        }
      ]
    },
    {
      "frames": [
        {
          "parts": [
            ""
          ]
        }
      ]
    }
  ]
}